AoikInspectArgs-0.2.0.dist-info/DESCRIPTION.rst
AoikInspectArgs-0.2.0.dist-info/METADATA
AoikInspectArgs-0.2.0.dist-info/RECORD
AoikInspectArgs-0.2.0.dist-info/WHEEL
AoikInspectArgs-0.2.0.dist-info/metadata.json
AoikInspectArgs-0.2.0.dist-info/top_level.txt
aoikinspectargs/__init__.py
aoikinspectargs/aoikenum.py
aoikinspectargs/aoikinspectargs.py
aoikinspectargs/aoikinspectargs_tests.py
