Metadata-Version: 2.0
Name: AoikInspectArgs
Version: 0.2.0
Summary: Inspect function arguments.
Home-page: https://github.com/AoiKuiyuyou/AoikInspectArgs
Author: Aoi.Kuiyuyou
Author-email: aoi.kuiyuyou@google.com
License: MIT
Keywords: inspect argument
Platform: UNKNOWN
Classifier: Development Status :: 3 - Alpha
Classifier: Intended Audience :: Developers
Classifier: License :: OSI Approved :: MIT License
Classifier: Programming Language :: Python :: 2
Classifier: Programming Language :: Python :: 2.7
Classifier: Programming Language :: Python :: 3
Classifier: Programming Language :: Python :: 3.5
